{"cameraMode":{"drawMode":0,"name":"Shaded","section":"Shading Mode"},"sceneLighting":true,"audioPlay":false,"sceneViewState":{"m_AlwaysRefresh":false,"showFog":true,"showSkybox":true,"showFlares":true,"showImageEffects":true,"showParticleSystems":true,"showVisualEffectGraphs":true,"m_FxEnabled":true},"in2DMode":false,"pivot":{"x":0.6886040568351746,"y":0.9966972470283508,"z":0.42169031500816347},"rotation":{"x":-0.21216334402561189,"y":0.5745133757591248,"z":-0.15733842551708222,"w":-0.774703860282898},"size":2.14350962638855,"orthographic":false}